LICENSE
MANIFEST.in
README.md
pyproject.toml
setup.py
csrc/fill_arguments.cuh
csrc/grouped_gemm.cu
csrc/grouped_gemm.h
csrc/ops.cu
grouped_gemm/__init__.py
grouped_gemm/backend.py
grouped_gemm/ops.py
grouped_gemm/ops_test.py
grouped_gemm_db.egg-info/PKG-INFO
grouped_gemm_db.egg-info/SOURCES.txt
grouped_gemm_db.egg-info/dependency_links.txt
grouped_gemm_db.egg-info/requires.txt
grouped_gemm_db.egg-info/top_level.txt
third_party/cutlass/include/cute/config.hpp
third_party/cutlass/include/cute/int_tuple.hpp
third_party/cutlass/include/cute/layout.hpp
third_party/cutlass/include/cute/layout_composed.hpp
third_party/cutlass/include/cute/pointer.hpp
third_party/cutlass/include/cute/stride.hpp
third_party/cutlass/include/cute/swizzle.hpp
third_party/cutlass/include/cute/swizzle_layout.hpp
third_party/cutlass/include/cute/swizzle_ptr.hpp
third_party/cutlass/include/cute/tensor.hpp
third_party/cutlass/include/cute/tensor_predicate.hpp
third_party/cutlass/include/cute/tile.hpp
third_party/cutlass/include/cute/underscore.hpp
third_party/cutlass/include/cute/algorithm/axpby.hpp
third_party/cutlass/include/cute/algorithm/clear.hpp
third_party/cutlass/include/cute/algorithm/copy.hpp
third_party/cutlass/include/cute/algorithm/fill.hpp
third_party/cutlass/include/cute/algorithm/functional.hpp
third_party/cutlass/include/cute/algorithm/gemm.hpp
third_party/cutlass/include/cute/algorithm/prefer.hpp
third_party/cutlass/include/cute/algorithm/tensor_algorithms.hpp
third_party/cutlass/include/cute/algorithm/tuple_algorithms.hpp
third_party/cutlass/include/cute/arch/cluster_sm90.hpp
third_party/cutlass/include/cute/arch/copy.hpp
third_party/cutlass/include/cute/arch/copy_sm75.hpp
third_party/cutlass/include/cute/arch/copy_sm80.hpp
third_party/cutlass/include/cute/arch/copy_sm90.hpp
third_party/cutlass/include/cute/arch/copy_sm90_desc.hpp
third_party/cutlass/include/cute/arch/copy_sm90_tma.hpp
third_party/cutlass/include/cute/arch/mma.hpp
third_party/cutlass/include/cute/arch/mma_sm61.hpp
third_party/cutlass/include/cute/arch/mma_sm70.hpp
third_party/cutlass/include/cute/arch/mma_sm75.hpp
third_party/cutlass/include/cute/arch/mma_sm80.hpp
