Metadata-Version: 2.4
Name: grouped-gemm-db
Version: 0.3.0
Summary: Grouped GEMM
License-File: LICENSE
Provides-Extra: dev
Requires-Dist: absl-py; extra == "dev"
Provides-Extra: all
Requires-Dist: absl-py; extra == "all"
Dynamic: description
Dynamic: description-content-type
Dynamic: license-file
Dynamic: provides-extra
Dynamic: summary
